howoldru.py
howoldru-0.1.2.dist-info/entry_points.txt
howoldru-0.1.2.dist-info/WHEEL
howoldru-0.1.2.dist-info/METADATA
howoldru-0.1.2.dist-info/RECORD
