Metadata-Version: 2.1
Name: howoldru
Version: 0.1.2
Summary: 
Home-page: https://github.com/kk6
License: UNKNOWN
Author: kk6
Author-email: hiro.ashiya@gmail.com
Requires-Python: >=3.7,<4.0
Classifier: Programming Language :: Python :: 3
Classifier: Programming Language :: Python :: 3.7
Requires-Dist: fire (>=0.1.3,<0.2.0)
Requires-Dist: pendulum (>=2.0,<3.0)
